{
    "sourceFile": ".gitignore",
    "activeCommit": 0,
    "commits": [
        {
            "activePatchIndex": 26,
            "patches": [
                {
                    "date": 1686144311349,
                    "content": "Index: \n===================================================================\n--- \n+++ \n"
                },
                {
                    "date": 1686245423957,
                    "content": "Index: \n===================================================================\n--- \n+++ \n@@ -1,12 +1,13 @@\n \r\n # Compiled class file\r\n *.class\r\n+*.exe\r\n \r\n-\r\n # Log file\r\n *.log\r\n \r\n+\r\n # BlueJ files\r\n *.ctxt\r\n \r\n # Mobile Tools for Java (J2ME)\r\n"
                },
                {
                    "date": 1686318626428,
                    "content": "Index: \n===================================================================\n--- \n+++ \n@@ -1,13 +1,14 @@\n \r\n+\r\n # Compiled class file\r\n *.class\r\n *.exe\r\n \r\n # Log file\r\n *.log\r\n+*.lh\r\n \r\n-\r\n # BlueJ files\r\n *.ctxt\r\n \r\n # Mobile Tools for Java (J2ME)\r\n"
                },
                {
                    "date": 1686318632071,
                    "content": "Index: \n===================================================================\n--- \n+++ \n@@ -1,6 +1,6 @@\n+*.txt\r\n \r\n-\r\n # Compiled class file\r\n *.class\r\n *.exe\r\n \r\n"
                },
                {
                    "date": 1686318641810,
                    "content": "Index: \n===================================================================\n--- \n+++ \n@@ -1,4 +1,5 @@\n+#input and output\r\n *.txt\r\n \r\n # Compiled class file\r\n *.class\r\n"
                },
                {
                    "date": 1686650833372,
                    "content": "Index: \n===================================================================\n--- \n+++ \n@@ -1,7 +1,6 @@\n-#input and output\r\n-*.txt\r\n \r\n+\r\n # Compiled class file\r\n *.class\r\n *.exe\r\n \r\n"
                },
                {
                    "date": 1687581872660,
                    "content": "Index: \n===================================================================\n--- \n+++ \n@@ -4,8 +4,9 @@\n *.class\r\n *.exe\r\n \r\n # Log file\r\n+\r\n *.log\r\n *.lh\r\n \r\n # BlueJ files\r\n"
                },
                {
                    "date": 1687581878587,
                    "content": "Index: \n===================================================================\n--- \n+++ \n@@ -4,9 +4,9 @@\n *.class\r\n *.exe\r\n \r\n # Log file\r\n-\r\n+*.vscode\r\n *.log\r\n *.lh\r\n \r\n # BlueJ files\r\n"
                },
                {
                    "date": 1691621342313,
                    "content": "Index: \n===================================================================\n--- \n+++ \n@@ -2,9 +2,9 @@\n \r\n # Compiled class file\r\n *.class\r\n *.exe\r\n-\r\n+*.bin\r\n # Log file\r\n *.vscode\r\n *.log\r\n *.lh\r\n"
                },
                {
                    "date": 1691621348970,
                    "content": "Index: \n===================================================================\n--- \n+++ \n@@ -4,8 +4,9 @@\n *.class\r\n *.exe\r\n *.bin\r\n # Log file\r\n+\r\n *.vscode\r\n *.log\r\n *.lh\r\n \r\n"
                },
                {
                    "date": 1691647771024,
                    "content": "Index: \n===================================================================\n--- \n+++ \n@@ -1,12 +1,13 @@\n+Output Files\r\n \r\n \r\n # Compiled class file\r\n *.class\r\n *.exe\r\n *.bin\r\n # Log file\r\n-\r\n+*.cph\r\n *.vscode\r\n *.log\r\n *.lh\r\n \r\n"
                },
                {
                    "date": 1691647778738,
                    "content": "Index: \n===================================================================\n--- \n+++ \n@@ -1,7 +1,7 @@\n-Output Files\r\n+# Output Files\r\n+*.txt\r\n \r\n-\r\n # Compiled class file\r\n *.class\r\n *.exe\r\n *.bin\r\n"
                },
                {
                    "date": 1691647795422,
                    "content": "Index: \n===================================================================\n--- \n+++ \n@@ -4,8 +4,9 @@\n # Compiled class file\r\n *.class\r\n *.exe\r\n *.bin\r\n+\r\n # Log file\r\n *.cph\r\n *.vscode\r\n *.log\r\n"
                },
                {
                    "date": 1691647818280,
                    "content": "Index: \n===================================================================\n--- \n+++ \n@@ -4,9 +4,9 @@\n # Compiled class file\r\n *.class\r\n *.exe\r\n *.bin\r\n-\r\n+*.ini\r\n # Log file\r\n *.cph\r\n *.vscode\r\n *.log\r\n"
                },
                {
                    "date": 1691647837840,
                    "content": "Index: \n===================================================================\n--- \n+++ \n@@ -6,9 +6,9 @@\n *.exe\r\n *.bin\r\n *.ini\r\n # Log file\r\n-*.cph\r\n+.cph\r\n *.vscode\r\n *.log\r\n *.lh\r\n \r\n"
                },
                {
                    "date": 1692088948455,
                    "content": "Index: \n===================================================================\n--- \n+++ \n@@ -1,6 +1,7 @@\n # Output Files\r\n *.txt\r\n+*.bin\r\n \r\n # Compiled class file\r\n *.class\r\n *.exe\r\n"
                },
                {
                    "date": 1692088969820,
                    "content": "Index: \n===================================================================\n--- \n+++ \n@@ -1,8 +1,8 @@\n # Output Files\r\n *.txt\r\n *.bin\r\n-\r\n+*.txt\r\n # Compiled class file\r\n *.class\r\n *.exe\r\n *.bin\r\n"
                },
                {
                    "date": 1695607234663,
                    "content": "Index: \n===================================================================\n--- \n+++ \n@@ -8,9 +8,9 @@\n *.bin\r\n *.ini\r\n # Log file\r\n .cph\r\n-*.vscode\r\n+.vscode\r\n *.log\r\n *.lh\r\n \r\n # BlueJ files\r\n"
                },
                {
                    "date": 1695607241588,
                    "content": "Index: \n===================================================================\n--- \n+++ \n@@ -10,9 +10,9 @@\n # Log file\r\n .cph\r\n .vscode\r\n *.log\r\n-*.lh\r\n+.lh\r\n \r\n # BlueJ files\r\n *.ctxt\r\n \r\n"
                },
                {
                    "date": 1695607339424,
                    "content": "Index: \n===================================================================\n--- \n+++ \n@@ -8,9 +8,9 @@\n *.bin\r\n *.ini\r\n # Log file\r\n .cph\r\n-.vscode\r\n+/.vscode\r\n *.log\r\n .lh\r\n \r\n # BlueJ files\r\n"
                },
                {
                    "date": 1695607441043,
                    "content": "Index: \n===================================================================\n--- \n+++ \n@@ -8,11 +8,11 @@\n *.bin\r\n *.ini\r\n # Log file\r\n .cph\r\n-/.vscode\r\n+.vscode\r\n *.log\r\n-.lh\r\n+/.lh\r\n \r\n # BlueJ files\r\n *.ctxt\r\n \r\n"
                },
                {
                    "date": 1695607447271,
                    "content": "Index: \n===================================================================\n--- \n+++ \n@@ -8,11 +8,11 @@\n *.bin\r\n *.ini\r\n # Log file\r\n .cph\r\n-.vscode\r\n+.vscode/\r\n *.log\r\n-/.lh\r\n+.lh/\r\n \r\n # BlueJ files\r\n *.ctxt\r\n \r\n"
                },
                {
                    "date": 1695607474124,
                    "content": "Index: \n===================================================================\n--- \n+++ \n@@ -8,9 +8,9 @@\n *.bin\r\n *.ini\r\n # Log file\r\n .cph\r\n-.vscode/\r\n+/.vscode/\r\n *.log\r\n .lh/\r\n \r\n # BlueJ files\r\n"
                },
                {
                    "date": 1695607481790,
                    "content": "Index: \n===================================================================\n--- \n+++ \n@@ -8,11 +8,11 @@\n *.bin\r\n *.ini\r\n # Log file\r\n .cph\r\n-/.vscode/\r\n+/.vscode\r\n *.log\r\n-.lh/\r\n+/.lh\r\n \r\n # BlueJ files\r\n *.ctxt\r\n \r\n"
                },
                {
                    "date": 1695607508001,
                    "content": "Index: \n===================================================================\n--- \n+++ \n@@ -8,9 +8,9 @@\n *.bin\r\n *.ini\r\n # Log file\r\n .cph\r\n-/.vscode\r\n+vscode\r\n *.log\r\n /.lh\r\n \r\n # BlueJ files\r\n"
                },
                {
                    "date": 1695607513616,
                    "content": "Index: \n===================================================================\n--- \n+++ \n@@ -0,0 +1,32 @@\n+# Output Files\r\n+*.txt\r\n+*.bin\r\n+*.txt\r\n+# Compiled class file\r\n+*.class\r\n+*.exe\r\n+*.bin\r\n+*.ini\r\n+# Log file\r\n+.cph\r\n+vscode/\r\n+*.log\r\n+/.lh/\r\n+\r\n+# BlueJ files\r\n+*.ctxt\r\n+\r\n+# Mobile Tools for Java (J2ME)\r\n+.mtj.tmp/\r\n+\r\n+# Package Files #\r\n+*.jar\r\n+*.war\r\n+*.nar\r\n+*.ear\r\n+*.zip\r\n+*.tar.gz\r\n+*.rar\r\n+\r\n+# virtual machine crash logs, see http://www.java.com/en/download/help/error_hotspot.xml\r\n+hs_err_pid*\n\\ No newline at end of file\n"
                },
                {
                    "date": 1695607544986,
                    "content": "Index: \n===================================================================\n--- \n+++ \n@@ -8,11 +8,11 @@\n *.bin\r\n *.ini\r\n # Log file\r\n .cph\r\n-vscode/\r\n+.vscode/\r\n *.log\r\n-/.lh/\r\n+.lh\r\n \r\n # BlueJ files\r\n *.ctxt\r\n \r\n@@ -28,37 +28,5 @@\n *.tar.gz\r\n *.rar\r\n \r\n # virtual machine crash logs, see http://www.java.com/en/download/help/error_hotspot.xml\r\n-hs_err_pid*\n-# Output Files\r\n-*.txt\r\n-*.bin\r\n-*.txt\r\n-# Compiled class file\r\n-*.class\r\n-*.exe\r\n-*.bin\r\n-*.ini\r\n-# Log file\r\n-.cph\r\n-vscode\r\n-*.log\r\n-/.lh\r\n-\r\n-# BlueJ files\r\n-*.ctxt\r\n-\r\n-# Mobile Tools for Java (J2ME)\r\n-.mtj.tmp/\r\n-\r\n-# Package Files #\r\n-*.jar\r\n-*.war\r\n-*.nar\r\n-*.ear\r\n-*.zip\r\n-*.tar.gz\r\n-*.rar\r\n-\r\n-# virtual machine crash logs, see http://www.java.com/en/download/help/error_hotspot.xml\r\n hs_err_pid*\n\\ No newline at end of file\n"
                }
            ],
            "date": 1686144311349,
            "name": "Commit-0",
            "content": "\r\n# Compiled class file\r\n*.class\r\n\r\n\r\n# Log file\r\n*.log\r\n\r\n# BlueJ files\r\n*.ctxt\r\n\r\n# Mobile Tools for Java (J2ME)\r\n.mtj.tmp/\r\n\r\n# Package Files #\r\n*.jar\r\n*.war\r\n*.nar\r\n*.ear\r\n*.zip\r\n*.tar.gz\r\n*.rar\r\n\r\n# virtual machine crash logs, see http://www.java.com/en/download/help/error_hotspot.xml\r\nhs_err_pid*"
        }
    ]
}